LICENSE
MANIFEST.in
README.rst
setup.py
docs/Makefile
docs/api.rst
docs/conf.py
docs/examples.rst
docs/index.rst
docs/installation.rst
docs/make.bat
docs/plugins.rst
docs/policy.rst
docs/report.rst
docs/scan.rst
docs/server.rst
docs/users.rst
nessus/__init__.py
python_nessus_client.egg-info/PKG-INFO
python_nessus_client.egg-info/SOURCES.txt
python_nessus_client.egg-info/dependency_links.txt
python_nessus_client.egg-info/not-zip-safe
python_nessus_client.egg-info/requires.txt
python_nessus_client.egg-info/top_level.txt