Metadata-Version: 1.1
Name: python-nessus-client
Version: 0.1.1
Summary: Python Client for Nessus REST API
Home-page: https://github.com/lukaszbanasiak/python-nessus-client
Author: Lukasz Banasiak
Author-email: lukas.banasiak@gmail.com
License: MIT
Keywords: nessus api rest client
Platform: UNKNOWN
Classifier: Development Status :: 3 - Alpha
Classifier: Environment :: Web Environment
Classifier: Intended Audience :: Developers
Classifier: License :: OSI Approved :: MIT License
Classifier: Operating System :: OS Independent
Classifier: Programming Language :: Python
Classifier: Programming Language :: Python :: 2
Classifier: Programming Language :: Python :: 2.7
Classifier: Topic :: Internet :: WWW/HTTP
Classifier: Topic :: Security
Classifier: Topic :: Software Development :: Libraries :: Python Modules
